MANIFEST.in
requirements.txt
setup.py
version.txt
docular/__init__.py
docular/constructors.py
docular/doc.py
docular/errors.py
docular/spec.py
docular.egg-info/PKG-INFO
docular.egg-info/SOURCES.txt
docular.egg-info/dependency_links.txt
docular.egg-info/top_level.txt