Metadata-Version: 1.0
Name: docular
Version: 0.4a2
Summary: Recursive object-documents
Home-page: UNKNOWN
Author: GRNET S.A.
Author-email: team@dev.grnet.gr
License: Affero GPL v3
Platform: UNKNOWN
